LICENSE.txt
MANIFEST.in
MiniVault.py
README.md
pyproject.toml
setup.cfg
setup.py
MiniVault.egg-info/PKG-INFO
MiniVault.egg-info/SOURCES.txt
MiniVault.egg-info/dependency_links.txt
MiniVault.egg-info/entry_points.txt
MiniVault.egg-info/top_level.txt