Metadata-Version: 2.2
Name: MiniVault
Version: 0.0.1
Summary: A simple, lightweight vault implemented in pure Python for securely storing and retrieving secrets in light-duty applications.
Home-page: https://github.com/mauricelambert/MiniVault
Author: Maurice Lambert
Author-email: Maurice Lambert <mauricelambert434@gmail.com>
Maintainer: Maurice Lambert
Maintainer-email: Maurice Lambert <mauricelambert434@gmail.com>
License: GPL-3.0 License
Project-URL: Github, https://github.com/mauricelambert/MiniVault
Project-URL: Documentation, https://mauricelambert.github.io/info/python/code/MiniVault.html
Keywords: vault,rc6,pure-python,lightweight-vault
Platform: Windows
Platform: Linux
Platform: MacOS
Classifier: Operating System :: POSIX
Classifier: Natural Language :: English
Classifier: Programming Language :: Python
Classifier: Intended Audience :: Developers
Classifier: Topic :: Security :: Cryptography
Classifier: Operating System :: MacOS :: MacOS X
Classifier: Programming Language :: Python :: 3.8
Classifier: Operating System :: Microsoft :: Windows
Classifier: Topic :: System :: Systems Administration
Classifier: Intended Audience :: System Administrators
Classifier: Topic :: Software Development :: Libraries
Classifier: Development Status :: 5 - Production/Stable
Classifier: License :: OSI Approved :: GNU General Public License v3 or later (GPLv3+)
Requires-Python: >=3.8
License-File: LICENSE.txt
Dynamic: author
Dynamic: home-page
Dynamic: maintainer
Dynamic: requires-python
